tabs_settings/.DS_Store
tabs_settings/__init__.py
tabs_settings/config/action_type.py
tabs_settings/config/asset_type.py
tabs_settings/config/backtest.py
tabs_settings/config/basket.py
tabs_settings/config/data_segment.py
tabs_settings/config/exchange_type.py
tabs_settings/config/fee.py
tabs_settings/config/fit.py
tabs_settings/config/horizon.py
tabs_settings/config/learn.py
tabs_settings/config/maturity.py
tabs_settings/config/oppfile.py
tabs_settings/config/partition.py
tabs_settings/config/roll.py
tabs_settings/config/rolling_learn.py
tabs_settings/config/search_space.py
tabs_settings/config/signal_builder.py
tabs_settings/config/stochastic_optimization.py
tabs_settings/config/storage.py
tabs_settings/config/threshold.py
tabs_settings/config/ticker.py
tabs_settings/config/trading_pair.py
tabs_settings/deploy.py
tabs_settings/settings/backfill/backtest.yml
tabs_settings/settings/backfill/model.yml
tabs_settings/settings/backfill/oppfile_gen.yml
tabs_settings/settings/backfill/score.yml
tabs_settings/settings/backfill/score_metric.yml
tabs_settings/settings/backfill/tactic_tuning.yml
tabs_settings/settings/learn.yaml
tabs_settings/settings/market_data.yml
tabs_settings/settings/paths.yml
tabs_settings/settings/prod.yml
tabs_settings/settings/test_market_data.yml
tabs_settings-0.1.1.dist-info/WHEEL
tabs_settings-0.1.1.dist-info/METADATA
tabs_settings-0.1.1.dist-info/RECORD
