Metadata-Version: 2.1
Name: tabs-settings
Version: 0.1.1
Summary: Handle all settings for tabs. Includes data download and storage.
License: MIT
Author-email: Alexis Rosuel <rosuelalexis1@gmail.com>
Requires-Python: >=3.11
Requires-Dist: immutables>=0.19
Requires-Dist: numpy>=1.24.2
Requires-Dist: pandas>=1.5.3
Requires-Dist: scikit-optimize>=0.9.0
